py_tictoc_timer/__init__.py
py_tictoc_timer/tictoc.py
py_tictoc_timer-2.1.1.dist-info/LICENSE
py_tictoc_timer-2.1.1.dist-info/METADATA
py_tictoc_timer-2.1.1.dist-info/WHEEL
py_tictoc_timer-2.1.1.dist-info/RECORD
