Metadata-Version: 2.1
Name: py-tictoc-timer
Version: 2.1.1
Summary: Time the execution of Python code using syntax similar to MATLAB's tic and toc functions.
Home-page: https://github.com/chrimaho/py-tictoc-timer.git
License: MIT
Author: Chris Mahoney
Author-email: chrismahoney@hotmail.com
Requires-Python: >=3.8,<4
Classifier: License :: OSI Approved :: MIT License
Classifier: Programming Language :: Python :: 3
Classifier: Programming Language :: Python :: 3.8
Classifier: Programming Language :: Python :: 3.9
Classifier: Programming Language :: Python :: 3.10
Classifier: Programming Language :: Python :: 3.11
Requires-Dist: typeguard (>=4.0,<5.0)
Project-URL: Repository, https://github.com/chrimaho/py-tictoc-timer.git
